README.md
setup.cfg
setup.py
src/rembg/__init__.py
src/rembg/bg.py
src/rembg/cmd/__init__.py
src/rembg/cmd/cli.py
src/rembg/cmd/server.py
src/rembg/u2net/__init__.py
src/rembg/u2net/data_loader.py
src/rembg/u2net/detect.py
src/rembg/u2net/u2net.py
src/rembg_cars.egg-info/PKG-INFO
src/rembg_cars.egg-info/SOURCES.txt
src/rembg_cars.egg-info/dependency_links.txt
src/rembg_cars.egg-info/entry_points.txt
src/rembg_cars.egg-info/requirements.txt
src/rembg_cars.egg-info/requires.txt
src/rembg_cars.egg-info/top_level.txt