Metadata-Version: 2.1
Name: rembg-cars
Version: 1.0.2
Summary: Remove image background from cars
Home-page: https://github.com/poropeza/rembg_cars
Author: Peter Oropeza
Author-email: peteroropeza2@gmail.com
License: UNKNOWN
Keywords: remove,background,u2net
Platform: UNKNOWN
Classifier: License :: OSI Approved :: MIT License
Classifier: Programming Language :: Python :: 3 :: Only
Requires-Python: >=3.8, <4
